{
    "China Super League": [
        {
            "Date": "11/04/2023",
            "HomeTeam_Name": "Nantong Zhiyun",
            "AwayTeam_Name": "Tianjin Teda",
            "HomeTeam_Score": "1",
            "AwayTeam_Score": "2",
            "Result": 1,
            "Source": "24Live.com"
        },
        {
            "Date": "11/04/2023",
            "HomeTeam_Name": "Shenzhen",
            "AwayTeam_Name": "Beijing Guoan",
            "HomeTeam_Score": "0",
            "AwayTeam_Score": "3",
            "Result": 1,
            "Source": "24Live.com"
        },
        {
            "Date": "11/04/2023",
            "HomeTeam_Name": "Changchun Yatai",
            "AwayTeam_Name": "Wuhan Three Towns",
            "HomeTeam_Score": "3",
            "AwayTeam_Score": "4",
            "Result": 1,
            "Source": "24Live.com"
        },
        {
            "Date": "11/04/2023",
            "HomeTeam_Name": "Shijiazhuang",
            "AwayTeam_Name": "Qingdao Jonoon",
            "HomeTeam_Score": "0",
            "AwayTeam_Score": "0",
            "Result": 2,
            "Source": "24Live.com"
        },
        {
            "Date": "11/04/2023",
            "HomeTeam_Name": "Dalian Pro",
            "AwayTeam_Name": "Shanghai SIPG",
            "HomeTeam_Score": "2",
            "AwayTeam_Score": "3",
            "Result": 1,
            "Source": "24Live.com"
        },
        {
            "Date": "11/04/2023",
            "HomeTeam_Name": "Shanghai Shenhua",
            "AwayTeam_Name": "Zhejiang Greentown",
            "HomeTeam_Score": "1",
            "AwayTeam_Score": "2",
            "Result": 1,
            "Source": "24Live.com"
        },
        {
            "Date": "11/04/2023",
            "HomeTeam_Name": "Chengdu Qianbao",
            "AwayTeam_Name": "Meizhou Hakka",
            "HomeTeam_Score": "3",
            "AwayTeam_Score": "0",
            "Result": 0,
            "Source": "24Live.com"
        },
        {
            "Date": "11/04/2023",
            "HomeTeam_Name": "Shandong Luneng",
            "AwayTeam_Name": "Henan Jianye",
            "HomeTeam_Score": "5",
            "AwayTeam_Score": "1",
            "Result": 0,
            "Source": "24Live.com"
        },
        {
            "Date": "10/29/2024",
            "HomeTeam_Name": "Meizhou Hakka",
            "AwayTeam_Name": "Nantong Zhiyun",
            "HomeTeam_Score": "0",
            "AwayTeam_Score": "4",
            "Result": 1,
            "Source": "24Live.com"
        },
        {
            "Date": "10/29/2024",
            "HomeTeam_Name": "Tianjin Teda",
            "AwayTeam_Name": "Shanghai Shenhua",
            "HomeTeam_Score": "1",
            "AwayTeam_Score": "1",
            "Result": 2,
            "Source": "24Live.com"
        },
        {
            "Date": "10/29/2024",
            "HomeTeam_Name": "Qingdao Jonoon",
            "AwayTeam_Name": "Dalian Pro",
            "HomeTeam_Score": "2",
            "AwayTeam_Score": "2",
            "Result": 2,
            "Source": "24Live.com"
        },
        {
            "Date": "10/29/2024",
            "HomeTeam_Name": "Henan Jianye",
            "AwayTeam_Name": "Changchun Yatai",
            "HomeTeam_Score": "1",
            "AwayTeam_Score": "1",
            "Result": 2,
            "Source": "24Live.com"
        },
        {
            "Date": "10/29/2024",
            "HomeTeam_Name": "Beijing Guoan",
            "AwayTeam_Name": "Chengdu Qianbao",
            "HomeTeam_Score": "2",
            "AwayTeam_Score": "3",
            "Result": 1,
            "Source": "24Live.com"
        },
        {
            "Date": "10/29/2024",
            "HomeTeam_Name": "Shanghai SIPG",
            "AwayTeam_Name": "Shandong Luneng",
            "HomeTeam_Score": "1",
            "AwayTeam_Score": "1",
            "Result": 2,
            "Source": "24Live.com"
        },
        {
            "Date": "10/29/2024",
            "HomeTeam_Name": "Zhejiang Greentown",
            "AwayTeam_Name": "Shijiazhuang",
            "HomeTeam_Score": "6",
            "AwayTeam_Score": "1",
            "Result": 0,
            "Source": "24Live.com"
        },
        {
            "Date": "10/29/2024",
            "HomeTeam_Name": "Wuhan Three Towns",
            "AwayTeam_Name": "Shenzhen",
            "HomeTeam_Score": "1",
            "AwayTeam_Score": "0",
            "Result": 0,
            "Source": "24Live.com"
        },
        {
            "Date": "10/23/2024",
            "HomeTeam_Name": "Chengdu Qianbao",
            "AwayTeam_Name": "Shenzhen",
            "HomeTeam_Score": "4",
            "AwayTeam_Score": "0",
            "Result": 0,
            "Source": "24Live.com"
        },
        {
            "Date": "10/22/2024",
            "HomeTeam_Name": "Qingdao Jonoon",
            "AwayTeam_Name": "Tianjin Teda",
            "HomeTeam_Score": "1",
            "AwayTeam_Score": "4",
            "Result": 1,
            "Source": "24Live.com"
        },
        {
            "Date": "10/21/2024",
            "HomeTeam_Name": "Nantong Zhiyun",
            "AwayTeam_Name": "Shanghai Shenhua",
            "HomeTeam_Score": "0",
            "AwayTeam_Score": "1",
            "Result": 1,
            "Source": "24Live.com"
        },
        {
            "Date": "10/21/2024",
            "HomeTeam_Name": "Henan Jianye",
            "AwayTeam_Name": "Shijiazhuang",
            "HomeTeam_Score": "6",
            "AwayTeam_Score": "0",
            "Result": 0,
            "Source": "24Live.com"
        },
        {
            "Date": "10/20/2024",
            "HomeTeam_Name": "Shanghai SIPG",
            "AwayTeam_Name": "Beijing Guoan",
            "HomeTeam_Score": "1",
            "AwayTeam_Score": "2",
            "Result": 1,
            "Source": "24Live.com"
        },
        {
            "Date": "10/20/2024",
            "HomeTeam_Name": "Dalian Pro",
            "AwayTeam_Name": "Wuhan Three Towns",
            "HomeTeam_Score": "1",
            "AwayTeam_Score": "3",
            "Result": 1,
            "Source": "24Live.com"
        },
        {
            "Date": "10/20/2024",
            "HomeTeam_Name": "Changchun Yatai",
            "AwayTeam_Name": "Shandong Luneng",
            "HomeTeam_Score": "0",
            "AwayTeam_Score": "3",
            "Result": 1,
            "Source": "24Live.com"
        },
        {
            "Date": "10/19/2024",
            "HomeTeam_Name": "Meizhou Hakka",
            "AwayTeam_Name": "Zhejiang Greentown",
            "HomeTeam_Score": "1",
            "AwayTeam_Score": "1",
            "Result": 2,
            "Source": "24Live.com"
        },
        {
            "Date": "09/30/2024",
            "HomeTeam_Name": "Shanghai Shenhua",
            "AwayTeam_Name": "Qingdao Jonoon",
            "HomeTeam_Score": "1",
            "AwayTeam_Score": "0",
            "Result": 0,
            "Source": "24Live.com"
        },
        {
            "Date": "09/30/2024",
            "HomeTeam_Name": "Zhejiang Greentown",
            "AwayTeam_Name": "Henan Jianye",
            "HomeTeam_Score": "3",
            "AwayTeam_Score": "0",
            "Result": 0,
            "Source": "24Live.com"
        },
        {
            "Date": "09/30/2024",
            "HomeTeam_Name": "Beijing Guoan",
            "AwayTeam_Name": "Dalian Pro",
            "HomeTeam_Score": "2",
            "AwayTeam_Score": "0",
            "Result": 0,
            "Source": "24Live.com"
        },
        {
            "Date": "09/29/2024",
            "HomeTeam_Name": "Nantong Zhiyun",
            "AwayTeam_Name": "Shanghai SIPG",
            "HomeTeam_Score": "0",
            "AwayTeam_Score": "1",
            "Result": 1,
            "Source": "24Live.com"
        },
        {
            "Date": "09/29/2024",
            "HomeTeam_Name": "Shenzhen",
            "AwayTeam_Name": "Changchun Yatai",
            "HomeTeam_Score": "0",
            "AwayTeam_Score": "1",
            "Result": 1,
            "Source": "24Live.com"
        },
        {
            "Date": "09/29/2024",
            "HomeTeam_Name": "Tianjin Teda",
            "AwayTeam_Name": "Chengdu Qianbao",
            "HomeTeam_Score": "2",
            "AwayTeam_Score": "2",
            "Result": 2,
            "Source": "24Live.com"
        },
        {
            "Date": "09/29/2024",
            "HomeTeam_Name": "Shandong Luneng",
            "AwayTeam_Name": "Wuhan Three Towns",
            "HomeTeam_Score": "2",
            "AwayTeam_Score": "1",
            "Result": 0,
            "Source": "24Live.com"
        },
        {
            "Date": "09/29/2024",
            "HomeTeam_Name": "Shijiazhuang",
            "AwayTeam_Name": "Meizhou Hakka",
            "HomeTeam_Score": "0",
            "AwayTeam_Score": "1",
            "Result": 1,
            "Source": "24Live.com"
        }
    ]
}